fnexchange_slack.py
fnexchange_slack-0.1.1.dist-info/DESCRIPTION.rst
fnexchange_slack-0.1.1.dist-info/METADATA
fnexchange_slack-0.1.1.dist-info/RECORD
fnexchange_slack-0.1.1.dist-info/WHEEL
fnexchange_slack-0.1.1.dist-info/metadata.json
fnexchange_slack-0.1.1.dist-info/top_level.txt
