Metadata-Version: 2.0
Name: fnexchange-slack
Version: 0.1.1
Summary: fnExchange plugin for Slack integration
Home-page: http://github.com/bhumilharia/fnexchange-slack
Author: Bhumil Haria
Author-email: bhumilharia@gmail.com
License: Apache
Keywords: fnexchange plugin
Platform: any
Classifier: Development Status :: 4 - Beta
Classifier: Intended Audience :: Developers
Classifier: License :: OSI Approved :: Apache Software License
Classifier: Operating System :: POSIX
Classifier: Operating System :: MacOS
Classifier: Operating System :: Unix
Classifier: Operating System :: Microsoft :: Windows
Classifier: Programming Language :: Python
Classifier: Programming Language :: Python :: 2
Classifier: Programming Language :: Python :: 3
Requires-Dist: fnexchange
Requires-Dist: requests (>=2.4.2)
